{
	"type": "object",
	"properties": {
		"Thematique": {
			"title": "Thematique",
			"type": "string",
			"enum": [ "Nature", "Architecture", "Mobilier", "Art", "Antiques", "Image & Son", "Collections", "Manuscrits & imprim\u00e9s", "Tribal & ethnologie", "Joaillerie et orfèvrerie", "Sciences et techniques", "Autres"]				
		},
		"Domaine": {
			"title": "Domaine",
			"enum": ["G\u00e9ologie / Min\u00e9raux","Botanique / Flore","Zoologie / Faune","Pal\u00e9ontologie","Parc &jardin","\u00e9difice","\u00e9dicule","Site","\u00e9l\u00e9ment d’architecture","Objet d’Art","Meuble","Arts d\u00e9coratifs","Dessin","Peinture","Sculpture","C\u00e9ramique","Verrerie","Ivoirerie","Objets arch\u00e9ologiques","Disque","Film","Instrument de musique","Objet sonore","Photographie","Cartes postales","Numismatique / Monnaies","Phal\u00e9ristique / M\u00e9dailles","Philat\u00e9lie / Timbres","Vinophilie / Vin","Ludophilie / jeux, jouets","Militaria","Transport","Livres","BD","Revues","Archives","Autographes","Ethnologie africaine","Ethnologie oc\u00e9anienne","Ethnologie am\u00e9ricaine","Ethnologie asiatique","Ethnologie europ\u00e9enne & r\u00e9gionale","Bijoux","Parures","Montres","Stylos","Objets scientifiques (m\u00e9decine, astronomie, physique…)","Objets techniques (agriculture, m\u00e9tiers…)"]
		},
		"Reference": {
			"title": "Reference",
			"type": "array",
			"items": {
				"type": "object",
				"properties": {
					"reference": {
						"title": "Reference",
						"type": "string"
					},
					"type_de_reference": {
						"title": "Type de reference",
						"enum": ["-", "Num\u00e9ros d'inventaire","N° de d\u00e9pôt","N° de prêt","Ancien N°","Autre N°","N° de rep\u00e9rage","Cote","ISBN","ISSN","N° d’\u00e9dition","R\u00e9f\u00e9rence","N° de renvoi","Identifiant","R\u00e9f\u00e9rence (d\u00e9jà mis)","N° provisoire","N° de bien"]
					}
				}
			}
		},
		"Designation": {
			"title": "Designation",
			"type": "array",
			"items": {
				"type": "object",
				"properties": {
					"designation": {
						"title": "Designation",
						"type": "string"
					},
					"type_de_designation": {
						"title": "Type de designation",
						"enum": ["D\u00e9nomination","Appellation","Nom vernaculaire","Titre","Titre en langue originale","Compl\u00e9ment de titre","D\u00e9nomination (d\u00e9jà saisi)","Sp\u00e9cimen","Intitul\u00e9","Nom","Autre nom","Objet"]
					}
				}
			}
		},
		"Description": {
			"type": "string",
			"title": "Description"
		},
		"Dimensions": {
			"title": "Dimensions",
			"type": "array",
			"items": {
				"type": "object",
				"properties": {
					"hauteur": {
						"title": "hauteur",
						"type": "string"
					},
					"largeur": {
						"title": "largeur",
						"type": "string"
					},
					"profondeur": {
						"title": "profondeur",
						"type": "string"
					},
					"poids": {
						"title": "poids",
						"type": "string"
					},
					"type": {
						"title": "type",
						"type": "string"
					}
				}
			}
		},
		"Inscriptions": {
			"title": "Inscriptions et Marques",
			"type": "array",
			"items": {
				"type": "object",
				"properties": {
					"Type de linscription": {
						"title": "Type de l'inscription",
						"type": "string"
					},
					"Emplacement de linscription": {
						"title": "Emplacement de l'inscription",
						"type": "string"
					},
					"Transcription de linscription": {
						"title": "Transcription de l'inscription",
						"type": "string"
					}
				}
			}
		},
		"Materiaux et techniques": {
			"title": "Matériaux et techniques",
			"type": "string"
			
		},
		"Personne": {
			"title": "Personne",
			"type": "array",
			"items": {
				"type": "object",
				"properties": {
					"nom": {
						"title": "nom",
						"type": "string"
					},
					"type": {
						"title":"type",
						"enum": ["Auteur","Artiste","Ex\u00e9cutant","Inventeur","Collecteur","D\u00e9couvreur","Utilisateur","Editeur","Concepteur","Architecte","R\u00e9colteur","D\u00e9terminateur","Photographe"]
					}
				}
			}
		},
		"Dates": {
			"title": "Dates",
			"type": "array",
			"items": {
				"type": "object",
				"properties": {
					"date": {
						"title": "Date",
						"type": "string"
					},
					"type_de_date": {
						"title": "Type de date",
						"enum": ["Dates de cr\u00e9ation","Dat\u00e9 d’ex\u00e9cution","Date de d\u00e9couverte","Date de collecte","Date d’utilisation","Date d’\u00e9dition","Date de publication","Date d’impression","Date de r\u00e9alisation","Date de construction","Date de r\u00e9colte","Date de d\u00e9termination","Date de prise de vue","Date de frappe"]
					}
				}
			}
		},
		"Lieux": {
			"title": "Lieux",
			"type": "array",
			"items": {
				"type": "object",
				"properties": {
					"nom": {
						"title": "Nom",
						"type": "string"
					},
					"type_de_lieu": {
						"title": "Type de lieu",
						"enum": ["Lieux de cr\u00e9ation","Lieux d'ex\u00e9cution","Lieux de d\u00e9couverte","Lieu de collecte","Lieu d’utilisation","Lieu d’\u00e9dition","Lieu de publication","Lieu d’impression","Lieu de r\u00e9alisation","Lieu de construction","Lieu de r\u00e9colte","Lieu de d\u00e9termination","Lieu de prise de vue","Lieu de frappe"]
					}
				}
			}
		},
		"Georeference": {
			"title": "Georeference",
			"type": "string"
		},
		"References bibliographiques": {
			"title": "Ref. bibliographiques",
			"type":"string"
		},
		"Liens externes": {
			"title": "Liens externes",
			"type": "array",
			"items": {
				"type": "object",
				"properties": {
					"url": {
						"title": "URL",
						"type": "string"
					},
					"libelle": {
						"title": "Libelle",
						"type": "string"
					}
				}
			}
		},
		"Localisation": {
			"title": "Localisation",
			"type": "array",
			"items": {
				"type": "object",
				"properties": {
					"nom": {
						"title": "nom",
						"type": "string"
					},
					"url": {
						"title": "url",
						"type": "string"
					}
				}
			}
		},
		"Etat": {
			"type": "string",
			"title": "Etat"
		},
		"Acquisition": {
			"type": "string",
			"title": "Acquisition"
		},
		"Assurance": {
			"type": "string",
			"title": "Assurance"
		},
		"Bloc-notes": {
			"type": "string",
			"title": "Bloc-note"
		}
	}
}